LICENSE
MANIFEST.in
README.rst
setup.cfg
setup.py
snakelet/__init__.py
snakelet/__main__.py
snakelet.egg-info/PKG-INFO
snakelet.egg-info/SOURCES.txt
snakelet.egg-info/dependency_links.txt
snakelet.egg-info/requires.txt
snakelet.egg-info/top_level.txt
snakelet/storage/__init__.py
snakelet/storage/annotation.py
snakelet/storage/collection.py
snakelet/storage/document.py
snakelet/storage/manager.py
snakelet/storage/paginator.py
snakelet/storage/proxy.py
snakelet/storage/query.py
snakelet/utilities/__init__.py
snakelet/utilities/conversion.py