Metadata-Version: 2.1
Name: snakelet
Version: 0.4.2
Summary: Mongo ORM
Home-page: https://github.com/alexgurrola/snakelet
Author: Alex Gurrola
Author-email: alexgurrola1@gmail.com
License: MIT
Keywords: data mongo orm
Platform: UNKNOWN
Classifier: Development Status :: 3 - Alpha
Classifier: Intended Audience :: Developers
Classifier: Topic :: Database :: Front-Ends
Classifier: License :: OSI Approved :: MIT License
Classifier: Programming Language :: Python :: 3
Classifier: Programming Language :: Python :: 3.5
Classifier: Programming Language :: Python :: 3.6
Provides-Extra: test
Provides-Extra: dev
